yahoo_finance_pynterface/__init__.py
yahoo_finance_pynterface/api.py
yahoo_finance_pynterface/core.py
yahoo_finance_pynterface-1.0.4.dist-info/METADATA
yahoo_finance_pynterface-1.0.4.dist-info/RECORD
yahoo_finance_pynterface-1.0.4.dist-info/WHEEL
yahoo_finance_pynterface-1.0.4.dist-info/top_level.txt
