Metadata-Version: 2.1
Name: yahoo-finance-pynterface
Version: 1.0.4
Summary: A Python Interface to the Yahoo Finance API
Home-page: https://github.com/andrea-dm/yahoo-finance-pynterface
Author: Andrea del Monaco
Author-email: and.delmonaco@gmail.com
License: UNKNOWN
Platform: UNKNOWN
Classifier: Programming Language :: Python :: 3.5
Classifier: Programming Language :: Python :: 3.6
Classifier: Programming Language :: Python :: 3.7
Classifier: License :: OSI Approved :: MIT License
Classifier: Operating System :: OS Independent
Classifier: Intended Audience :: Science/Research
Classifier: Intended Audience :: Financial and Insurance Industry
